setup.py
morgaroth_docker/DockerRegistryClient.py
morgaroth_docker.egg-info/PKG-INFO
morgaroth_docker.egg-info/SOURCES.txt
morgaroth_docker.egg-info/dependency_links.txt
morgaroth_docker.egg-info/not-zip-safe
morgaroth_docker.egg-info/top_level.txt