Metadata-Version: 1.1
Name: morgaroth-docker
Version: 0.0.1
Summary: Morgaroths Docker Client
Home-page: https://github.com/Morgaroth/morgaroth-docker
Author: Mateusz Jaje
Author-email: mateuszjaje@gmail.com
License: MIT
Platform: UNKNOWN
Classifier: Development Status :: 2 - Pre-Alpha
Classifier: License :: OSI Approved :: GNU General Public License v3 or later (GPLv3+)
Classifier: Programming Language :: Python :: 3 :: Only
